psrs/__init__.py
psrs/psrs.py
psrs/utils.py
psrs-0.1.0.dist-info/licenses/LICENSE
psrs-0.1.0.dist-info/METADATA
psrs-0.1.0.dist-info/WHEEL
psrs-0.1.0.dist-info/top_level.txt
psrs-0.1.0.dist-info/RECORD
