Metadata-Version: 2.4
Name: psrs
Version: 0.1.0
Summary: Procrustes Similarity with the Reconstructed Space
Author-email: Javad Haashemi <mj.haashemi@gmail.com>
License: Copyright (c) 2024 Javad Hashemi
Project-URL: Homepage, https://github.com/javad-hashemi/psrs
Project-URL: BugTracker, https://github.com/javad-hashemi/psrs/issues
Classifier: Programming Language :: Python :: 3
Classifier: License :: Other/Proprietary License
Classifier: Intended Audience :: Science/Research
Classifier: Operating System :: OS Independent
Classifier: Development Status :: 3 - Alpha
Requires-Python: >=3.7
License-File: LICENSE
Requires-Dist: numpy>=1.21.0
Requires-Dist: torch>=2.0.0
Requires-Dist: scikit-learn>=1.0.0
Requires-Dist: scipy>=1.7.0
Dynamic: license-file
